.gitignore
CHANGELOG.md
LICENSE
MANIFEST.in
README.md
requirements.txt
setup.py
.github/workflows/main.yml
sourcecred/__init__.py
sourcecred/client.py
sourcecred/version.py
sourcecred.egg-info/PKG-INFO
sourcecred.egg-info/SOURCES.txt
sourcecred.egg-info/dependency_links.txt
sourcecred.egg-info/entry_points.txt
sourcecred.egg-info/not-zip-safe
sourcecred.egg-info/requires.txt
sourcecred.egg-info/top_level.txt